supersk_python_docs/__init__.py
supersk_python_docs/_version.py
supersk_python_docs/layout.html
supersk_python_docs/theme.conf
supersk_python_docs/static/custom_pydoctheme.css_t
supersk_python_docs-0.0.0.dist-info/LICENSE
supersk_python_docs-0.0.0.dist-info/METADATA
supersk_python_docs-0.0.0.dist-info/WHEEL
supersk_python_docs-0.0.0.dist-info/entry_points.txt
supersk_python_docs-0.0.0.dist-info/top_level.txt
supersk_python_docs-0.0.0.dist-info/RECORD
